{
  "id": 18,
  "globalId": "34ea7d25-d3a1-488b-b98b-dc1efb78b353",
  "namespace": {
    "id": 1,
    "globalId": "18a50b84-e914-49c9-9d75-654a0042e784",
    "name": "PAASysUpdates",
    "description": "",
    "isSystem": true
  },
  "name": "VersionConvert",
  "description": "",
  "parser": "<parser><type>string</type><replace>false</replace><decodeHtml>false</decodeHtml></parser>",
  "defaultValue": "",
  "cacheTime": 0,
  "cacheLayer": "Global",
  "src": {
    "language": "csharp",
    "compiledRazorLocation": "host",
    "additionalAssemblies": "",
    "debug": false,
    "type": "razor"
  }
}